py_tps/__init__.py
py_tps/tps_io.py
py_tps-0.1.7.dist-info/LICENSE
py_tps-0.1.7.dist-info/WHEEL
py_tps-0.1.7.dist-info/METADATA
py_tps-0.1.7.dist-info/RECORD
