Metadata-Version: 2.1
Name: py-tps
Version: 0.1.7
Summary: This is a simple library for reading and writing .tps files as created and used by the tpsDig landmarking tool created by F. James Rohlf.  https://life.bio.sunysb.edu/morph/
License: MIT
Author: ryanfeather
Requires-Python: >=3.6,<4.0
Classifier: Intended Audience :: Science/Research
Classifier: License :: OSI Approved :: MIT License
Classifier: Programming Language :: Python :: 3
Classifier: Programming Language :: Python :: 3.6
Classifier: Programming Language :: Python :: 3.7
Requires-Dist: numpy (>=1.14,<2.0)
